ktoolbox/__init__.py
ktoolbox/__main__.py
ktoolbox/_cli_zh.py
ktoolbox/_configuration_zh.py
ktoolbox/_enum.py
ktoolbox/action/__init__.py
ktoolbox/action/base.py
ktoolbox/action/fetch.py
ktoolbox/action/job.py
ktoolbox/action/search.py
ktoolbox/action/utils.py
ktoolbox/api/__init__.py
ktoolbox/api/base.py
ktoolbox/api/misc/__init__.py
ktoolbox/api/misc/get_app_version.py
ktoolbox/api/model/__init__.py
ktoolbox/api/model/announcement.py
ktoolbox/api/model/creator.py
ktoolbox/api/model/post.py
ktoolbox/api/posts/__init__.py
ktoolbox/api/posts/get_announcement.py
ktoolbox/api/posts/get_creator_post.py
ktoolbox/api/posts/get_creators.py
ktoolbox/api/posts/get_post.py
ktoolbox/api/posts/get_post_revisions.py
ktoolbox/api/utils.py
ktoolbox/cli.py
ktoolbox/configuration.py
ktoolbox/downloader/__init__.py
ktoolbox/downloader/base.py
ktoolbox/downloader/downloader.py
ktoolbox/downloader/utils.py
ktoolbox/job/__init__.py
ktoolbox/job/model.py
ktoolbox/job/runner.py
ktoolbox/model.py
ktoolbox/progress.py
ktoolbox/utils.py
ktoolbox_pure_py-0.24.0.dist-info/METADATA
ktoolbox_pure_py-0.24.0.dist-info/WHEEL
ktoolbox_pure_py-0.24.0.dist-info/entry_points.txt
ktoolbox_pure_py-0.24.0.dist-info/licenses/LICENSE
ktoolbox_pure_py-0.24.0.dist-info/RECORD
