Metadata-Version: 2.4
Name: ktoolbox-pure-py
Version: 0.24.0
Summary: A useful CLI tool for downloading posts in Kemono.cr / .su / .party
License: BSD-3-Clause
License-File: LICENSE
Keywords: kemono,kemono.cr,kemono.su,kemono.party,cli-app,downloader,os-independent
Author: Ljzd-PRO
Author-email: me@ljzd.link
Requires-Python: >=3.8,<3.14
Classifier: Development Status :: 5 - Production/Stable
Classifier: License :: OSI Approved :: BSD License
Classifier: Operating System :: OS Independent
Classifier: Programming Language :: Python :: 3
Classifier: Programming Language :: Python :: 3.8
Classifier: Programming Language :: Python :: 3.9
Classifier: Programming Language :: Python :: 3.10
Classifier: Programming Language :: Python :: 3.11
Classifier: Programming Language :: Python :: 3.12
Classifier: Programming Language :: Python :: 3.13
Classifier: Topic :: Terminals
Provides-Extra: uvloop
Requires-Dist: aiofiles (>=23.2.1,<24.0.0)
Requires-Dist: fire (>=0.5,<0.8)
Requires-Dist: httpx[socks] (>=0.24.1,<0.28.0)
Requires-Dist: loguru (>=0.7.2,<0.8.0)
Requires-Dist: pathvalidate (>=3.2.0,<4.0.0)
Requires-Dist: pydantic[dotenv] (>=1.10.13,<2.0.0)
Requires-Dist: rich (>=14.1.0,<15.0.0)
Requires-Dist: tenacity (>=8.2.3,<9.0.0)
Requires-Dist: tqdm (>=4.66.1,<5.0.0)
Requires-Dist: uvloop (>=0.19.0,<0.20.0) ; extra == "uvloop"
Project-URL: Bug Tracker, https://github.com/Ljzd-PRO/KToolBox/issues
Project-URL: Documentation, https://ktoolbox.readthedocs.io/
Project-URL: Homepage, https://ktoolbox.readthedocs.io/
Project-URL: Repository, https://github.com/Ljzd-PRO/KToolBox
